ntt_signal/Exceptions.py
ntt_signal/Signal.py
ntt_signal/__init__.py
tests/SignalTest.py
tests/__init__.py
ntt_signal-1.0.3.dist-info/LICENSE
ntt_signal-1.0.3.dist-info/METADATA
ntt_signal-1.0.3.dist-info/WHEEL
ntt_signal-1.0.3.dist-info/top_level.txt
ntt_signal-1.0.3.dist-info/RECORD
