Metadata-Version: 2.1
Name: ntt-signal
Version: 1.0.3
Summary: Small library for observation mechanism
Home-page: https://github.com/threezinedine/ntt-signal
Author: threezinedine
Author-email: threezinedine@email.com
License: UNKNOWN
Project-URL: Source, https://github.com/threezinedine/ntt-signal
Project-URL: Tracker, https://github.com/threezinedine/ntt-signal/issues
Keywords: dependency injector
Platform: UNKNOWN
Classifier: Development Status :: 3 - Alpha
Classifier: Intended Audience :: Developers
Classifier: Programming Language :: Python :: 3
Classifier: Programming Language :: Python :: 3.6
Classifier: Programming Language :: Python :: 3.7
Classifier: Programming Language :: Python :: 3.8
Classifier: Programming Language :: Python :: 3.9
License-File: LICENSE
